README.md
cropper.py
setup.py
momo_cropper.egg-info/PKG-INFO
momo_cropper.egg-info/SOURCES.txt
momo_cropper.egg-info/dependency_links.txt
momo_cropper.egg-info/entry_points.txt
momo_cropper.egg-info/requires.txt
momo_cropper.egg-info/top_level.txt
tools/__init__.py
tools/img_utils.py
tools/rgb_utils.py
tools/utils.py