Metadata-Version: 1.0
Name: momo-cropper
Version: 0.0.2
Summary: An image cropping tool by given border colors.
Home-page: UNKNOWN
Author: Momo
Author-email: 1447340425@qq.com
License: MIT licence
Keywords: cropper,image
Platform: any
